Metadata-Version: 2.1
Name: django-hyval
Version: 1.0.0
Summary: Encryption over django CharField
Home-page: https://github.com/coci/django-hyval
Author: Soroush Safari
Author-email: soroush.safari1992@gmail.com
License: GPLv3
Platform: UNKNOWN
Classifier: Operating System :: OS Independent
Classifier: License :: OSI Approved :: GNU General Public License v3 (GPLv3)
Classifier: Programming Language :: Python :: 3.6
Classifier: Programming Language :: Python :: 3.7
Classifier: Programming Language :: Python :: 3.8
Classifier: Programming Language :: Python :: 3.9
Requires-Python: >=3.6
